webpagetest/__init__.py
webpagetest/__main__.py
webpagetest/main.py
webpagetest/utils.py
webpagetest-0.2.dist-info/DESCRIPTION.rst
webpagetest-0.2.dist-info/entry_points.txt
webpagetest-0.2.dist-info/METADATA
webpagetest-0.2.dist-info/metadata.json
webpagetest-0.2.dist-info/RECORD
webpagetest-0.2.dist-info/top_level.txt
webpagetest-0.2.dist-info/WHEEL
